html_diff/__init__.py
html_diff/__main__.py
html_diff/check.py
html_diff/config.py
html_diff/legacy.py
html_diff-0.4.1.dist-info/LICENSE
html_diff-0.4.1.dist-info/WHEEL
html_diff-0.4.1.dist-info/METADATA
html_diff-0.4.1.dist-info/RECORD
