Metadata-Version: 2.1
Name: html-diff
Version: 0.4.1
Summary: HTML-formatted diff'ing of HTML snippets
Home-page: https://gitlab.com/matpi/html-diff
License: AGPL-3.0+
Keywords: html,diff
Author: Quentin Wenger
Author-email: quentin.wenger@oly-exams.org
Requires-Python: >=3.5,<4.0
Classifier: Development Status :: 4 - Beta
Classifier: Environment :: Console
Classifier: Environment :: Web Environment
Classifier: License :: OSI Approved :: GNU Affero General Public License v3 or later (AGPLv3+)
Classifier: License :: Other/Proprietary License
Classifier: Operating System :: OS Independent
Classifier: Programming Language :: Python :: 3
Classifier: Programming Language :: Python :: 3.5
Classifier: Programming Language :: Python :: 3.6
Classifier: Programming Language :: Python :: 3.7
Classifier: Programming Language :: Python :: 3.8
Classifier: Programming Language :: Python :: 3.9
Classifier: Topic :: Internet
Classifier: Topic :: Internet :: WWW/HTTP :: Dynamic Content
Classifier: Topic :: Software Development
Classifier: Topic :: Text Processing :: Markup :: HTML
Requires-Dist: beautifulsoup4 (>=4.8,<5.0)
Project-URL: Repository, https://gitlab.com/matpi/html-diff
